{"nodes": [{"id": "At_attention", "height": 50}, {"id": "Victor_Emmanuel_III_of_Italy", "height": 50}, {"id": "At_attention", "height": 50}, {"id": "General-purpose_computing_on_graphics_processing_units", "height": 50}, {"id": "Fullerene", "height": 50}, {"id": "General-purpose_computing_on_graphics_processing_units", "height": 50}, {"id": "Concentric_zone_model", "height": 50}, {"id": "Page_layout", "height": 50}, {"id": "Blended_learning", "height": 50}, {"id": "Westboro_Baptist_Church", "height": 50}, {"id": "Order", "height": 50}, {"id": "Westboro_Baptist_Church", "height": 50}, {"id": "Judgment_of_Paris", "height": 50}, {"id": "Page_layout", "height": 50}, {"id": "Stephen_Colbert", "height": 50}, {"id": "Page_layout", "height": 50}, {"id": "Complex_system", "height": 50}, {"id": "Scientific_control", "height": 50}], "edges": [{"from": "At_attention", "to": "Victor_Emmanuel_III_of_Italy", "relation": "execute"}, {"from": "At_attention", "to": "General-purpose_computing_on_graphics_processing_units", "relation": "execute"}, {"from": "Fullerene", "to": "General-purpose_computing_on_graphics_processing_units", "relation": "execute"}, {"from": "Concentric_zone_model", "to": "Page_layout", "relation": "depict"}, {"from": "Blended_learning", "to": "Westboro_Baptist_Church", "relation": "give"}, {"from": "Order", "to": "Westboro_Baptist_Church", "relation": "give"}, {"from": "Judgment_of_Paris", "to": "Page_layout", "relation": "plot"}, {"from": "Stephen_Colbert", "to": "Page_layout", "relation": "plot"}, {"from": "Complex_system", "to": "Scientific_control", "relation": "brake"}]}